umlaut/__init__.py
umlaut/examples/__init__.py
umlaut/examples/run_model_example.py
umlaut/examples/track_model_example.py
umlaut/umlaut.py
umlaut-0.3.4.dist-info/LICENSE
umlaut-0.3.4.dist-info/WHEEL
umlaut-0.3.4.dist-info/METADATA
umlaut-0.3.4.dist-info/RECORD
