Metadata-Version: 2.1
Name: umlaut
Version: 0.3.4
Summary: A simpler way to work with MLflow
Home-page: https://github.com/DOTONESIX/Umlaut
Keywords: mlops,mlflow,devops
Author: DOTONESIX
Author-email: contact@dotonesix.com
Requires-Python: >=3.9.12,<4.0
Classifier: Programming Language :: Python :: 3
Classifier: Programming Language :: Python :: 3.10
Requires-Dist: mlflow (==1.28.0)
Requires-Dist: psycopg2 (==2.9.3)
Project-URL: Repository, https://github.com/DOTONESIX/Umlaut
